grid_control_api.py
grid_control_settings.py
python_compat.py
python_compat_json.py
python_compat_popen2.py
python_compat_tarfile.py
python_compat_urllib2.py
grid_control/.PLUGINS
grid_control/__init__.py
grid_control/event_base.py
grid_control/event_basic.py
grid_control/gc_exceptions.py
grid_control/gc_plugin.py
grid_control/gui.py
grid_control/job_db.py
grid_control/job_db_text.py
grid_control/job_db_zip.py
grid_control/job_definition.py
grid_control/job_manager.py
grid_control/job_selector.py
grid_control/logging_setup.py
grid_control/output_processor.py
grid_control/report.py
grid_control/stream_base.py
grid_control/workflow.py
grid_control/backends/__init__.py
grid_control/backends/access.py
grid_control/backends/access_afs.py
grid_control/backends/access_arc.py
grid_control/backends/access_grid.py
grid_control/backends/access_voms.py
grid_control/backends/aspect_cancel.py
grid_control/backends/aspect_output.py
grid_control/backends/aspect_status.py
grid_control/backends/backend_tools.py
grid_control/backends/broker_base.py
grid_control/backends/broker_basic.py
grid_control/backends/jdl_writer.py
grid_control/backends/logged_process.py
grid_control/backends/storage.py
grid_control/backends/wms.py
grid_control/backends/wms_arc.py
grid_control/backends/wms_condor.py
grid_control/backends/wms_cream.py
grid_control/backends/wms_edg.py
grid_control/backends/wms_glite.py
grid_control/backends/wms_glitewms.py
grid_control/backends/wms_glitewms_direct.py
grid_control/backends/wms_grid.py
grid_control/backends/wms_gridengine.py
grid_control/backends/wms_host.py
grid_control/backends/wms_inactive.py
grid_control/backends/wms_jms.py
grid_control/backends/wms_local.py
grid_control/backends/wms_lsf.py
grid_control/backends/wms_multi.py
grid_control/backends/wms_pbs.py
grid_control/backends/wms_pbsge.py
grid_control/backends/wms_slurm.py
grid_control/backends/wms_thread.py
grid_control-1.9.82.dist-info/DESCRIPTION.rst
grid_control-1.9.82.dist-info/METADATA
grid_control-1.9.82.dist-info/RECORD
grid_control-1.9.82.dist-info/WHEEL
grid_control-1.9.82.dist-info/entry_points.txt
grid_control-1.9.82.dist-info/metadata.json
grid_control-1.9.82.dist-info/top_level.txt
